[
    {
        "value": "Acha\u00c3\u00afa",
        "key": 2879
    },
    {
        "value": "Agio Oros",
        "key": 2929
    },
    {
        "value": "Arg\u00f3lida",
        "key": 2881
    },
    {
        "value": "Arkadia",
        "key": 2882
    },
    {
        "value": "Arta",
        "key": 2883
    },
    {
        "value": "Attiki",
        "key": 2884
    },
    {
        "value": "Chalkidiki",
        "key": 2885
    },
    {
        "value": "Chania",
        "key": 2886
    },
    {
        "value": "Chios",
        "key": 2887
    },
    {
        "value": "Dodekanisos",
        "key": 2888
    },
    {
        "value": "Drama",
        "key": 2889
    },
    {
        "value": "\u00c9lide",
        "key": 2897
    },
    {
        "value": "Emacia",
        "key": 2898
    },
    {
        "value": "Etolia-Acarnania",
        "key": 2880
    },
    {
        "value": "Euritania",
        "key": 2891
    },
    {
        "value": "Evros",
        "key": 2890
    },
    {
        "value": "Evvoia",
        "key": 2892
    },
    {
        "value": "Florina",
        "key": 2893
    },
    {
        "value": "Fokis",
        "key": 2894
    },
    {
        "value": "Fthiotis",
        "key": 2895
    },
    {
        "value": "Grevena",
        "key": 2896
    },
    {
        "value": "Ioannina",
        "key": 2899
    },
    {
        "value": "Irakleion",
        "key": 2900
    },
    {
        "value": "Karditsa",
        "key": 2901
    },
    {
        "value": "Kastoria",
        "key": 2902
    },
    {
        "value": "Kavalla",
        "key": 2903
    },
    {
        "value": "Kefallinia",
        "key": 2904
    },
    {
        "value": "Kerkyra",
        "key": 2905
    },
    {
        "value": "Kilkis",
        "key": 2906
    },
    {
        "value": "Korinthia",
        "key": 2907
    },
    {
        "value": "Kozani",
        "key": 2908
    },
    {
        "value": "Kyklades",
        "key": 2909
    },
    {
        "value": "Laconia",
        "key": 2910
    },
    {
        "value": "Larisa",
        "key": 2911
    },
    {
        "value": "Lasithion",
        "key": 2912
    },
    {
        "value": "Lefkas",
        "key": 2913
    },
    {
        "value": "Lesvos",
        "key": 2914
    },
    {
        "value": "Magnisia",
        "key": 2915
    },
    {
        "value": "Mesenia",
        "key": 2916
    },
    {
        "value": "Pella",
        "key": 2917
    },
    {
        "value": "Pieria",
        "key": 10181
    },
    {
        "value": "Preveza",
        "key": 2918
    },
    {
        "value": "Rethymnon",
        "key": 2919
    },
    {
        "value": "Rodopi",
        "key": 2920
    },
    {
        "value": "Samos",
        "key": 2921
    },
    {
        "value": "Serrai",
        "key": 2922
    },
    {
        "value": "Tesal\u00f3nica",
        "key": 2924
    },
    {
        "value": "Tespr\u00f3tida",
        "key": 2923
    },
    {
        "value": "Trikala",
        "key": 2925
    },
    {
        "value": "Voiotia",
        "key": 2926
    },
    {
        "value": "Xanthi",
        "key": 2927
    },
    {
        "value": "Zakynthos",
        "key": 2928
    }
]